{"version":3,"kind":"Notebook","sha256":"1c579c9726c74eccbfca8a4e37043479cbcb580aec0bd577b2367bc8b3d42711","slug":"notebooks.dask-cluster","location":"/notebooks/04-dask-cluster.ipynb","dependencies":[],"frontmatter":{"title":"Dask Schedulers","content_includes_title":true,"kernelspec":{"name":"python3","display_name":"Python 3 (ipykernel)","language":"python"},"authors":[{"nameParsed":{"literal":"Negin Sobhani","given":"Negin","family":"Sobhani"},"name":"Negin Sobhani","id":"contributors-myst-generated-uid-0"},{"nameParsed":{"literal":"Brian Vanderwende","given":"Brian","family":"Vanderwende"},"name":"Brian Vanderwende","id":"contributors-myst-generated-uid-1"},{"nameParsed":{"literal":"Deepak Cherian","given":"Deepak","family":"Cherian"},"name":"Deepak Cherian","id":"contributors-myst-generated-uid-2"},{"nameParsed":{"literal":"Ben Kirk","given":"Ben","family":"Kirk"},"name":"Ben Kirk","id":"contributors-myst-generated-uid-3"}],"open_access":true,"license":{"content":{"id":"CC-BY-4.0","url":"https://creativecommons.org/licenses/by/4.0/","name":"Creative Commons Attribution 4.0 International","free":true,"CC":true},"code":{"id":"Apache-2.0","url":"https://opensource.org/licenses/Apache-2.0","name":"Apache License 2.0","free":true,"osi":true}},"github":"https://github.com/projectpythia/dask-cookbook","copyright":"2024","affiliations":[{"id":"UAlbany","name":"University at Albany (SUNY)","department":"Atmospheric and Environmental Sciences","url":"https://www.albany.edu/daes"},{"id":"CISL","name":"NSF National Center for Atmospheric Research","department":"Computational and Information Systems Lab","url":"https://www.cisl.ucar.edu"},{"id":"Unidata","name":"NSF Unidata","url":"https://www.unidata.ucar.edu"},{"id":"Argonne","name":"Argonne National Laboratory","department":"Environmental Science Division","url":"https://www.anl.gov/evs"},{"id":"CarbonPlan","name":"CarbonPlan","url":"https://carbonplan.org"},{"id":"NVIDIA","name":"NVIDIA Corporation","url":"https://www.nvidia.com/"}],"numbering":{"title":{"offset":1}},"source_url":"https://github.com/projectpythia/dask-cookbook/blob/main/notebooks/04-dask-cluster.ipynb","edit_url":"https://github.com/projectpythia/dask-cookbook/edit/main/notebooks/04-dask-cluster.ipynb","thumbnail":"/dask-cookbook/_preview/30/build/efb0893141695015b5a57e9702d22b2e.svg","exports":[{"format":"ipynb","filename":"04-dask-cluster.ipynb","url":"/dask-cookbook/_preview/30/build/04-dask-cluster-ba6e9e70867b6d456ec2d1f363a60868.ipynb"}]},"widgets":{"application/vnd.jupyter.widget-state+json":{"state":{},"version_major":2,"version_minor":0}},"mdast":{"type":"root","children":[{"type":"block","kind":"notebook-content","children":[{"type":"paragraph","position":{"start":{"line":1,"column":1},"end":{"line":5,"column":1}},"children":[{"type":"image","url":"/dask-cookbook/_preview/30/build/efb0893141695015b5a57e9702d22b2e.svg","alt":"Dask logo","width":"30%","key":"gbi6OvnmMt","urlSource":"https://docs.dask.org/en/stable/_images/dask_horizontal.svg"}],"key":"wjIEtYy20B"},{"type":"heading","depth":1,"position":{"start":{"line":7,"column":1},"end":{"line":7,"column":1}},"children":[{"type":"text","value":"Dask Schedulers","position":{"start":{"line":7,"column":1},"end":{"line":7,"column":1}},"key":"xDwx9ko8uu"}],"identifier":"dask-schedulers","label":"Dask Schedulers","html_id":"dask-schedulers","implicit":true,"key":"g4c1A3cWfr"},{"type":"heading","depth":3,"position":{"start":{"line":9,"column":1},"end":{"line":9,"column":1}},"children":[{"type":"text","value":"In this tutorial, you learn:","position":{"start":{"line":9,"column":1},"end":{"line":9,"column":1}},"key":"OXiUFkS7Jk"}],"identifier":"in-this-tutorial-you-learn","label":"In this tutorial, you learn:","html_id":"in-this-tutorial-you-learn","implicit":true,"key":"ek3SY4I0bj"},{"type":"list","ordered":false,"spread":false,"position":{"start":{"line":11,"column":1},"end":{"line":15,"column":1}},"children":[{"type":"listItem","spread":true,"position":{"start":{"line":11,"column":1},"end":{"line":11,"column":1}},"children":[{"type":"paragraph","children":[{"type":"text","value":"Components of Dask Schedulers","position":{"start":{"line":11,"column":1},"end":{"line":11,"column":1}},"key":"XipSRHgykH"}],"key":"dBFh2Ch600"}],"key":"Ltl2L8qYiS"},{"type":"listItem","spread":true,"position":{"start":{"line":12,"column":1},"end":{"line":12,"column":1}},"children":[{"type":"paragraph","children":[{"type":"text","value":"Types of Dask Schedulers","position":{"start":{"line":12,"column":1},"end":{"line":12,"column":1}},"key":"R4W5Z1Cywo"}],"key":"TRF3qHDqEK"}],"key":"IcouWWqsL7"},{"type":"listItem","spread":true,"position":{"start":{"line":13,"column":1},"end":{"line":15,"column":1}},"children":[{"type":"paragraph","children":[{"type":"text","value":"Single Machine Schedulers","position":{"start":{"line":13,"column":1},"end":{"line":13,"column":1}},"key":"QIgraKE06z"}],"key":"PzPYBrxu1X"}],"key":"OvhWCKT9LM"}],"key":"viTdzATK2W"},{"type":"paragraph","position":{"start":{"line":16,"column":1},"end":{"line":16,"column":1}},"children":[{"type":"strong","position":{"start":{"line":16,"column":1},"end":{"line":16,"column":1}},"children":[{"type":"text","value":"Related Documentation","position":{"start":{"line":16,"column":1},"end":{"line":16,"column":1}},"key":"m1xTAOqGp7"}],"key":"zn7SEW8OOk"}],"key":"Ik8ZBUxJBO"},{"type":"list","ordered":false,"spread":false,"position":{"start":{"line":18,"column":1},"end":{"line":20,"column":1}},"children":[{"type":"listItem","spread":true,"position":{"start":{"line":18,"column":1},"end":{"line":18,"column":1}},"children":[{"type":"paragraph","children":[{"type":"link","url":"https://docs.dask.org/en/stable/scheduling.html","position":{"start":{"line":18,"column":1},"end":{"line":18,"column":1}},"children":[{"type":"text","value":"Dask Scheduling","position":{"start":{"line":18,"column":1},"end":{"line":18,"column":1}},"key":"ApPZEucpwZ"}],"urlSource":"https://docs.dask.org/en/stable/scheduling.html","key":"KotLnjxJQK"}],"key":"NF6WF3YcxV"}],"key":"kOB4KZw6Up"},{"type":"listItem","spread":true,"position":{"start":{"line":19,"column":1},"end":{"line":19,"column":1}},"children":[{"type":"paragraph","children":[{"type":"link","url":"https://docs.dask.org/en/stable/deploying-python.html","position":{"start":{"line":19,"column":1},"end":{"line":19,"column":1}},"children":[{"type":"text","value":"Dask Local Cluster","position":{"start":{"line":19,"column":1},"end":{"line":19,"column":1}},"key":"yJMxGeTPrt"}],"urlSource":"https://docs.dask.org/en/stable/deploying-python.html","key":"zzl3fMEcO1"}],"key":"TIv2udMPdU"}],"key":"T5fjfRc8Qv"},{"type":"listItem","spread":true,"position":{"start":{"line":20,"column":1},"end":{"line":20,"column":1}},"children":[{"type":"paragraph","children":[{"type":"link","url":"https://docs.dask.org/en/stable/deploying.html","position":{"start":{"line":20,"column":1},"end":{"line":20,"column":1}},"children":[{"type":"text","value":"Deploying Dask Cluster Manager","position":{"start":{"line":20,"column":1},"end":{"line":20,"column":1}},"key":"mBVExCohl3"}],"urlSource":"https://docs.dask.org/en/stable/deploying.html","key":"qGwO2qYynK"}],"key":"JdMw1niB8w"}],"key":"wJO78rWA50"}],"key":"taUcHHecui"}],"key":"i0jVNHOwni"},{"type":"block","kind":"notebook-content","data":{"tags":[]},"children":[{"type":"heading","depth":2,"position":{"start":{"line":1,"column":1},"end":{"line":1,"column":1}},"children":[{"type":"text","value":"Introduction","position":{"start":{"line":1,"column":1},"end":{"line":1,"column":1}},"key":"EbIt7WMHhW"}],"identifier":"introduction","label":"Introduction","html_id":"introduction","implicit":true,"key":"jtqdBR7UWl"},{"type":"paragraph","position":{"start":{"line":2,"column":1},"end":{"line":2,"column":1}},"children":[{"type":"text","value":"As we mentioned in our Dask overview, Dask is composed of two main parts:","position":{"start":{"line":2,"column":1},"end":{"line":2,"column":1}},"key":"DajXMQXVHN"}],"key":"uGgG858Tf6"},{"type":"list","ordered":true,"start":1,"spread":false,"position":{"start":{"line":4,"column":1},"end":{"line":6,"column":1}},"children":[{"type":"listItem","spread":true,"position":{"start":{"line":4,"column":1},"end":{"line":4,"column":1}},"children":[{"type":"paragraph","children":[{"type":"text","value":"Dask Collections (APIs)","position":{"start":{"line":4,"column":1},"end":{"line":4,"column":1}},"key":"XhMEwc3aRQ"}],"key":"mTj8jh53ps"}],"key":"phaDfOtcsJ"},{"type":"listItem","spread":true,"position":{"start":{"line":5,"column":1},"end":{"line":6,"column":1}},"children":[{"type":"paragraph","children":[{"type":"text","value":"Dynamic Task Scheduling","position":{"start":{"line":5,"column":1},"end":{"line":5,"column":1}},"key":"PTocw3Ecve"}],"key":"daujRv9BBo"}],"key":"VaCvhZUHKs"}],"key":"OGJtVXsiND"},{"type":"paragraph","position":{"start":{"line":7,"column":1},"end":{"line":7,"column":1}},"children":[{"type":"text","value":"So far, we have talked about different Dask collections, but in this tutorial we are going to talk more about the second part.","position":{"start":{"line":7,"column":1},"end":{"line":7,"column":1}},"key":"tD4g3cTW22"}],"key":"nbjvwBPUix"},{"type":"heading","depth":2,"position":{"start":{"line":10,"column":1},"end":{"line":10,"column":1}},"children":[{"type":"text","value":"The Dask scheduler - our task orchestrator","position":{"start":{"line":10,"column":1},"end":{"line":10,"column":1}},"key":"MttZxFbr1W"}],"identifier":"the-dask-scheduler-our-task-orchestrator","label":"The Dask scheduler - our task orchestrator","html_id":"the-dask-scheduler-our-task-orchestrator","implicit":true,"key":"bG50OAEiWn"},{"type":"paragraph","position":{"start":{"line":12,"column":1},"end":{"line":12,"column":1}},"children":[{"type":"text","value":"The ","position":{"start":{"line":12,"column":1},"end":{"line":12,"column":1}},"key":"rZKPRYRXXp"},{"type":"inlineCode","value":"Dask.distributed","position":{"start":{"line":12,"column":1},"end":{"line":12,"column":1}},"key":"ri6I5nKFKm"},{"type":"text","value":" task ","position":{"start":{"line":12,"column":1},"end":{"line":12,"column":1}},"key":"tQxCiBT4L0"},{"type":"emphasis","position":{"start":{"line":12,"column":1},"end":{"line":12,"column":1}},"children":[{"type":"text","value":"scheduler","position":{"start":{"line":12,"column":1},"end":{"line":12,"column":1}},"key":"PCdjHSLbxp"}],"key":"zqDWWIthPj"},{"type":"text","value":" is a centralized, dynamic system that coordinates the efforts of various dask ","position":{"start":{"line":12,"column":1},"end":{"line":12,"column":1}},"key":"MXmSYEgq3L"},{"type":"emphasis","position":{"start":{"line":12,"column":1},"end":{"line":12,"column":1}},"children":[{"type":"text","value":"worker","position":{"start":{"line":12,"column":1},"end":{"line":12,"column":1}},"key":"UJE8eoxdBZ"}],"key":"l7UNWIGk7A"},{"type":"text","value":" processes spread accross different machines.","position":{"start":{"line":12,"column":1},"end":{"line":12,"column":1}},"key":"J6iYRmCV0K"}],"key":"VbKDXaUbZZ"},{"type":"paragraph","position":{"start":{"line":14,"column":1},"end":{"line":14,"column":1}},"children":[{"type":"text","value":"When a computational task is submitted, the Dask distributed ","position":{"start":{"line":14,"column":1},"end":{"line":14,"column":1}},"key":"sRe5qUFvWU"},{"type":"emphasis","position":{"start":{"line":14,"column":1},"end":{"line":14,"column":1}},"children":[{"type":"text","value":"scheduler","position":{"start":{"line":14,"column":1},"end":{"line":14,"column":1}},"key":"qLKI9Oflzk"}],"key":"JBxdumN15d"},{"type":"text","value":" sends it off to a Dask ","position":{"start":{"line":14,"column":1},"end":{"line":14,"column":1}},"key":"rhxZ6RPObc"},{"type":"emphasis","position":{"start":{"line":14,"column":1},"end":{"line":14,"column":1}},"children":[{"type":"text","value":"cluster","position":{"start":{"line":14,"column":1},"end":{"line":14,"column":1}},"key":"Wzy9tzP7Xf"}],"key":"J4frmXcATL"},{"type":"text","value":" - simply a collection of Dask ","position":{"start":{"line":14,"column":1},"end":{"line":14,"column":1}},"key":"FyBJBJ9Ur5"},{"type":"emphasis","position":{"start":{"line":14,"column":1},"end":{"line":14,"column":1}},"children":[{"type":"text","value":"workers","position":{"start":{"line":14,"column":1},"end":{"line":14,"column":1}},"key":"QBrk6WKeva"}],"key":"tRn8XyPBVU"},{"type":"text","value":". A worker is typically a separate Python process on either the local host or a remote machine.","position":{"start":{"line":14,"column":1},"end":{"line":14,"column":1}},"key":"wTCb9MFQ80"}],"key":"EN4G7LQgYn"},{"type":"paragraph","position":{"start":{"line":16,"column":1},"end":{"line":16,"column":1}},"children":[{"type":"text","value":"To perform work, a scheduler must be assigned resources in the form of a Dask cluster. The cluster consists of the following components:","position":{"start":{"line":16,"column":1},"end":{"line":16,"column":1}},"key":"Np5GWP6VkH"}],"key":"MLh2FwlUr7"},{"type":"list","ordered":false,"spread":false,"position":{"start":{"line":18,"column":1},"end":{"line":23,"column":1}},"children":[{"type":"listItem","spread":true,"position":{"start":{"line":18,"column":1},"end":{"line":19,"column":1}},"children":[{"type":"paragraph","position":{"start":{"line":18,"column":1},"end":{"line":18,"column":1}},"children":[{"type":"strong","position":{"start":{"line":18,"column":1},"end":{"line":18,"column":1}},"children":[{"type":"text","value":"scheduler","position":{"start":{"line":18,"column":1},"end":{"line":18,"column":1}},"key":"tW00tpUfUw"}],"key":"xW0vxhxIDi"},{"type":"text","value":" : A scheduler creates and manages task graphs and distributes tasks to workers.","position":{"start":{"line":18,"column":1},"end":{"line":18,"column":1}},"key":"bu4y4TRDrR"}],"key":"TkPQv8reVE"}],"key":"lfhFQyKTvi"},{"type":"listItem","spread":true,"position":{"start":{"line":20,"column":1},"end":{"line":21,"column":1}},"children":[{"type":"paragraph","position":{"start":{"line":20,"column":1},"end":{"line":20,"column":1}},"children":[{"type":"strong","position":{"start":{"line":20,"column":1},"end":{"line":20,"column":1}},"children":[{"type":"text","value":"workers","position":{"start":{"line":20,"column":1},"end":{"line":20,"column":1}},"key":"RwImzSoX0W"}],"key":"sXSpj6KkdF"},{"type":"text","value":" : A worker is typically a separate Python process on either the local host or a remote machine. A Dask ","position":{"start":{"line":20,"column":1},"end":{"line":20,"column":1}},"key":"cvazer7U9I"},{"type":"strong","position":{"start":{"line":20,"column":1},"end":{"line":20,"column":1}},"children":[{"type":"text","value":"cluster","position":{"start":{"line":20,"column":1},"end":{"line":20,"column":1}},"key":"XUd9jfklPI"}],"key":"LBhyrsIvW0"},{"type":"text","value":" usually consists of many workers. Basically, a worker is a Python interpretor which will perform work on a subset of our dataset.","position":{"start":{"line":20,"column":1},"end":{"line":20,"column":1}},"key":"IOhgkzmYIb"}],"key":"YrHxk8w1KT"}],"key":"LcWHEG6zjs"},{"type":"listItem","spread":true,"position":{"start":{"line":22,"column":1},"end":{"line":23,"column":1}},"children":[{"type":"paragraph","position":{"start":{"line":22,"column":1},"end":{"line":22,"column":1}},"children":[{"type":"strong","position":{"start":{"line":22,"column":1},"end":{"line":22,"column":1}},"children":[{"type":"text","value":"client","position":{"start":{"line":22,"column":1},"end":{"line":22,"column":1}},"key":"JtAKOJdkSY"}],"key":"z5RgLlhjzh"},{"type":"text","value":" - A high-level interface that points to the scheduler (often local but not always). A client serves as the entry point for interacting with a Dask scheduler.","position":{"start":{"line":22,"column":1},"end":{"line":22,"column":1}},"key":"WrovvJGPVn"}],"key":"dOftOXJyln"}],"key":"k52v13wepL"}],"key":"MEDiJbdIpx"},{"type":"paragraph","position":{"start":{"line":24,"column":1},"end":{"line":26,"column":1}},"children":[{"type":"image","url":"/dask-cookbook/_preview/30/build/7445a9f1307deaa4760238b8ed4d85c3.png","alt":"Dask Distributed Cluster","width":"75%","key":"E7BZKdjZYp","urlSource":"https://tutorial.dask.org/_images/distributed-overview.png"}],"key":"Ppt1jxROga"},{"type":"paragraph","position":{"start":{"line":28,"column":1},"end":{"line":28,"column":1}},"children":[{"type":"emphasis","position":{"start":{"line":28,"column":1},"end":{"line":28,"column":1}},"children":[{"type":"text","value":"Image credit: Dask Contributors","position":{"start":{"line":28,"column":1},"end":{"line":28,"column":1}},"key":"Ki3Oi6WwYa"}],"key":"jo0qy5o3Su"}],"key":"G7wSgmQoSz"}],"visibility":"show","key":"BmEbe12VKM"},{"type":"block","kind":"notebook-content","children":[{"type":"heading","depth":2,"position":{"start":{"line":1,"column":1},"end":{"line":1,"column":1}},"children":[{"type":"text","value":"Schedulers","position":{"start":{"line":1,"column":1},"end":{"line":1,"column":1}},"key":"fM5jMPCQ33"}],"identifier":"schedulers","label":"Schedulers","html_id":"schedulers","implicit":true,"key":"F4BJ9ZNOXW"},{"type":"paragraph","position":{"start":{"line":2,"column":1},"end":{"line":2,"column":1}},"children":[{"type":"text","value":"Dask essentially offers two types of schedulers:","position":{"start":{"line":2,"column":1},"end":{"line":2,"column":1}},"key":"ekthDjNvzo"}],"key":"MU1mUXj8vI"},{"type":"image","style":{"verticalAlign":"middle","margin":"30px 0px"},"url":"/dask-cookbook/_preview/30/build/8b6da849318d7659184d63558507155e.svg","alt":"High level collections are used to generate task graphs which can be executed by schedulers on a single machine or a cluster.","width":"75%","key":"xq4xawjciq","urlSource":"https://docs.dask.org/en/stable/_images/dask-overview.svg"},{"type":"paragraph","position":{"start":{"line":7,"column":1},"end":{"line":7,"column":1}},"children":[{"type":"emphasis","position":{"start":{"line":7,"column":1},"end":{"line":7,"column":1}},"children":[{"type":"text","value":"Image credit: Dask Contributors","position":{"start":{"line":7,"column":1},"end":{"line":7,"column":1}},"key":"m33ZSp1JmZ"}],"key":"eq7KOZaEGw"}],"key":"UqFcIwjC2g"},{"type":"heading","depth":3,"position":{"start":{"line":9,"column":1},"end":{"line":9,"column":1}},"children":[{"type":"text","value":"1. Single machine scheduler","position":{"start":{"line":9,"column":1},"end":{"line":9,"column":1}},"key":"YPLhGbNjw5"}],"identifier":"id-1-single-machine-scheduler","label":"1. Single machine scheduler","html_id":"id-1-single-machine-scheduler","implicit":true,"key":"MeTEUO7HkO"},{"type":"list","ordered":false,"spread":false,"position":{"start":{"line":10,"column":1},"end":{"line":13,"column":1}},"children":[{"type":"listItem","spread":true,"position":{"start":{"line":10,"column":1},"end":{"line":10,"column":1}},"children":[{"type":"paragraph","children":[{"type":"text","value":"The Single-machine Scheduler schedules tasks and manages the execution of those tasks on the same machine where the scheduler is running.","position":{"start":{"line":10,"column":1},"end":{"line":10,"column":1}},"key":"TcGBkVLFl7"}],"key":"DSIFNppYO0"}],"key":"Ed9kQdTMrr"},{"type":"listItem","spread":true,"position":{"start":{"line":11,"column":1},"end":{"line":11,"column":1}},"children":[{"type":"paragraph","children":[{"type":"text","value":"It is designed to be used in situations where the amount of data or the computational requirements are too large for a single process to handle, but not large enough to warrant the use of a cluster of machines.","position":{"start":{"line":11,"column":1},"end":{"line":11,"column":1}},"key":"Rxp0oKxgsK"}],"key":"Ccv8MjrhHg"}],"key":"i1xQqRKvzo"},{"type":"listItem","spread":true,"position":{"start":{"line":12,"column":1},"end":{"line":13,"column":1}},"children":[{"type":"paragraph","children":[{"type":"text","value":"It is relatively simple and cheap to use but it does not scale as it only runs on a single machine.","position":{"start":{"line":12,"column":1},"end":{"line":12,"column":1}},"key":"ORC59yqEzj"}],"key":"RrKaPNSv7c"}],"key":"voj7JDrQK8"}],"key":"akGw7YmSgH"},{"type":"paragraph","position":{"start":{"line":14,"column":1},"end":{"line":14,"column":1}},"children":[{"type":"strong","position":{"start":{"line":14,"column":1},"end":{"line":14,"column":1}},"children":[{"type":"text","value":"Single machine scheduler is the default choice used by Dask.","position":{"start":{"line":14,"column":1},"end":{"line":14,"column":1}},"key":"L2uwLBMmOf"}],"key":"Q6XStniGtA"}],"key":"QHBt3ZymwE"},{"type":"paragraph","position":{"start":{"line":16,"column":1},"end":{"line":16,"column":1}},"children":[{"type":"text","value":"In Dask, there are several types of single machine schedulers that can be used to schedule computations on a single machine:","position":{"start":{"line":16,"column":1},"end":{"line":16,"column":1}},"key":"sgay06Z2rz"}],"key":"dlORiXzIgs"},{"type":"heading","depth":4,"position":{"start":{"line":17,"column":1},"end":{"line":17,"column":1}},"children":[{"type":"text","value":"1.1. Single-threaded scheduler","position":{"start":{"line":17,"column":1},"end":{"line":17,"column":1}},"key":"y6hW4aUFBP"}],"identifier":"id-1-1-single-threaded-scheduler","label":"1.1. Single-threaded scheduler","html_id":"id-1-1-single-threaded-scheduler","implicit":true,"key":"vk6KoHuehh"},{"type":"paragraph","position":{"start":{"line":18,"column":1},"end":{"line":19,"column":1}},"children":[{"type":"text","value":"This scheduler runs all tasks ","position":{"start":{"line":18,"column":1},"end":{"line":18,"column":1}},"key":"Kh80pDyRu7"},{"type":"strong","position":{"start":{"line":18,"column":1},"end":{"line":18,"column":1}},"children":[{"type":"text","value":"serially","position":{"start":{"line":18,"column":1},"end":{"line":18,"column":1}},"key":"fg1yi4aBLk"}],"key":"MynqZPkb7b"},{"type":"text","value":" on a single thread.","position":{"start":{"line":18,"column":1},"end":{"line":18,"column":1}},"key":"euDqAPZmWn"},{"type":"break","position":{"start":{"line":18,"column":1},"end":{"line":18,"column":1}},"key":"QGmeTmzbR7"},{"type":"text","value":"This is only useful for debugging and profiling, but does not have any parallelization.","position":{"start":{"line":18,"column":1},"end":{"line":18,"column":1}},"key":"CWvgUVVXKG"}],"key":"Xrwz3CVxMn"},{"type":"heading","depth":4,"position":{"start":{"line":21,"column":1},"end":{"line":21,"column":1}},"children":[{"type":"text","value":"1.2. Threaded scheduler","position":{"start":{"line":21,"column":1},"end":{"line":21,"column":1}},"key":"UZMdDfl7QR"}],"identifier":"id-1-2-threaded-scheduler","label":"1.2. Threaded scheduler","html_id":"id-1-2-threaded-scheduler","implicit":true,"key":"cNBsL55n4f"},{"type":"paragraph","position":{"start":{"line":22,"column":1},"end":{"line":23,"column":1}},"children":[{"type":"text","value":"The threaded scheduler uses a pool of ","position":{"start":{"line":22,"column":1},"end":{"line":22,"column":1}},"key":"axsKOPvNxl"},{"type":"strong","position":{"start":{"line":22,"column":1},"end":{"line":22,"column":1}},"children":[{"type":"text","value":"local","position":{"start":{"line":22,"column":1},"end":{"line":22,"column":1}},"key":"HLV2JkmO3v"}],"key":"t8jM4hxlu3"},{"type":"text","value":" threads to execute tasks concurrently.","position":{"start":{"line":22,"column":1},"end":{"line":22,"column":1}},"key":"R9mnPRJPlk"},{"type":"break","position":{"start":{"line":22,"column":1},"end":{"line":22,"column":1}},"key":"jt7g2UTrml"},{"type":"text","value":"This is the default scheduler for Dask, and is suitable for most use cases on a single machine. Multithreading works well for Dask Array and Dask DataFrame.","position":{"start":{"line":22,"column":1},"end":{"line":22,"column":1}},"key":"hl2fO4fuJn"}],"key":"EECd1EWjnE"},{"type":"paragraph","position":{"start":{"line":25,"column":1},"end":{"line":25,"column":1}},"children":[{"type":"text","value":"To select one of the above scheduler for your computation, you can specify it when doing ","position":{"start":{"line":25,"column":1},"end":{"line":25,"column":1}},"key":"y9ijwXC0Ko"},{"type":"inlineCode","value":".compute()","position":{"start":{"line":25,"column":1},"end":{"line":25,"column":1}},"key":"P9QWxxL3Y2"},{"type":"text","value":":","position":{"start":{"line":25,"column":1},"end":{"line":25,"column":1}},"key":"gqG2MCw7YS"}],"key":"m3rgcYRkEp"},{"type":"paragraph","position":{"start":{"line":27,"column":1},"end":{"line":27,"column":1}},"children":[{"type":"text","value":"For example:","position":{"start":{"line":27,"column":1},"end":{"line":27,"column":1}},"key":"gNufBKKb0L"}],"key":"M4kDTG6o3n"},{"type":"code","lang":"python","value":"this.compute(scheduler=\"single-threaded\")  # for debugging and profiling only","position":{"start":{"line":28,"column":1},"end":{"line":30,"column":1}},"key":"x2ZTZn9tOS"},{"type":"paragraph","position":{"start":{"line":33,"column":1},"end":{"line":33,"column":1}},"children":[{"type":"text","value":"As mentioned above the ","position":{"start":{"line":33,"column":1},"end":{"line":33,"column":1}},"key":"mgi3avnDog"},{"type":"emphasis","position":{"start":{"line":33,"column":1},"end":{"line":33,"column":1}},"children":[{"type":"text","value":"threaded scheduler","position":{"start":{"line":33,"column":1},"end":{"line":33,"column":1}},"key":"ihvmP8xfSm"}],"key":"PxgXLOeRWN"},{"type":"text","value":" is the default scheduler in Dask. But you can set the default scheduler to Single-threaded or multi-processing by:","position":{"start":{"line":33,"column":1},"end":{"line":33,"column":1}},"key":"WeAIXifMQG"}],"key":"V1gXTToxo1"},{"type":"code","lang":"python","value":"import dask\ndask.config.set(scheduler='synchronous')  # overwrite default with single-threaded scheduler","position":{"start":{"line":35,"column":1},"end":{"line":38,"column":1}},"key":"MO624wWVxY"},{"type":"paragraph","position":{"start":{"line":40,"column":1},"end":{"line":40,"column":1}},"children":[{"type":"text","value":"Multi-processing works well for pure Python code - ","position":{"start":{"line":40,"column":1},"end":{"line":40,"column":1}},"key":"e5K5OASY3G"},{"type":"emphasis","position":{"start":{"line":40,"column":1},"end":{"line":40,"column":1}},"children":[{"type":"text","value":"delayed","position":{"start":{"line":40,"column":1},"end":{"line":40,"column":1}},"key":"q0pmhtgOJl"}],"key":"GweqnsxJCc"},{"type":"text","value":" functions and operations on Dask Bags.","position":{"start":{"line":40,"column":1},"end":{"line":40,"column":1}},"key":"VIaEZyuhYM"}],"key":"wtsduqoxDQ"},{"type":"paragraph","position":{"start":{"line":42,"column":1},"end":{"line":42,"column":1}},"children":[{"type":"text","value":"Let’s compare the performance of each of these single-machine schedulers:","position":{"start":{"line":42,"column":1},"end":{"line":42,"column":1}},"key":"HkL1v3ptEZ"}],"key":"YVK3cSw5Lc"}],"key":"t0Hd4apgv2"},{"type":"block","kind":"notebook-code","children":[{"type":"code","lang":"python","executable":true,"value":"import numpy as np\nimport dask.array as da","key":"kUHIwVCdRL"},{"type":"outputs","id":"XFplz-hTAHu-MnJKGrkGi","children":[],"key":"FYjEFkRX1G"}],"key":"lqw9Au3D7Z"},{"type":"block","kind":"notebook-code","children":[{"type":"code","lang":"python","executable":true,"value":"%%time\n## - numpy performance\nxn = np.random.normal(10, 0.1, size=(20_000, 20_000))\nyn = xn.mean(axis=0)\nyn","key":"M7TiP3AWB5"},{"type":"outputs","id":"WlS4KZZv5bZyu1kWgyP8M","children":[{"type":"output","children":[],"jupyter_data":{"output_type":"stream","name":"stdout","text":"CPU times: user 9.16 s, sys: 174 ms, total: 9.34 s\nWall time: 9.42 s\n"},"key":"raNqw0DRbQ"},{"type":"output","children":[],"jupyter_data":{"output_type":"execute_result","execution_count":2,"metadata":{},"data":{"text/plain":{"content":"array([ 9.99952775,  9.99985462, 10.0001354 , ..., 10.00070903,\n        9.99988077, 10.00109345], shape=(20000,))","content_type":"text/plain"}}},"key":"HRry2h43D1"}],"key":"J6AzidRep9"}],"key":"lHNAXiG6yb"},{"type":"block","kind":"notebook-code","children":[{"type":"code","lang":"python","executable":true,"value":"%%time\n# -- dask array using the default\nxd = da.random.normal(10, 0.1, size=(20_000, 20_000), chunks=(2000, 2000))\nyd = xd.mean(axis=0)\nyd.compute()","key":"OzHKznS8Cn"},{"type":"outputs","id":"NrB3iBQeYrTcQ_n7WKx0Z","children":[{"type":"output","children":[],"jupyter_data":{"output_type":"stream","name":"stdout","text":"CPU times: user 13.6 s, sys: 97 ms, total: 13.7 s\nWall time: 6.41 s\n"},"key":"BTfMTrA0V4"},{"type":"output","children":[],"jupyter_data":{"output_type":"execute_result","execution_count":3,"metadata":{},"data":{"text/plain":{"content":"array([10.00043851, 10.00031033,  9.99983874, ..., 10.00021063,\n        9.99991772, 10.00028391], shape=(20000,))","content_type":"text/plain"}}},"key":"Xx0pPu2mnj"}],"key":"NdQkZ4a4AH"}],"key":"G42hE41GtW"},{"type":"block","kind":"notebook-code","children":[{"type":"code","lang":"python","executable":true,"value":"import time\n# -- dask testing different schedulers:\nfor sch in ['threading', 'processes', 'sync']:\n    t0 = time.time()\n    r = yd.compute(scheduler=sch)\n    t1 = time.time()\n    print(f\"{sch:>10} :  {t1 - t0:0.4f} s\")","key":"AHKM4bo3Dh"},{"type":"outputs","id":"X0hy-NuE2UaCOJ3TYyae1","children":[{"type":"output","children":[],"jupyter_data":{"output_type":"stream","name":"stdout","text":" threading :  4.7381 s\n"},"key":"Cez1o4LkAy"},{"type":"output","children":[],"jupyter_data":{"output_type":"stream","name":"stdout","text":" processes :  9.9354 s\n"},"key":"vEQusmUin4"},{"type":"output","children":[],"jupyter_data":{"output_type":"stream","name":"stdout","text":"      sync :  13.6105 s\n"},"key":"HvjUN0aCsd"}],"key":"it4xWdm4f3"}],"key":"y83az7Xy7G"},{"type":"block","kind":"notebook-code","children":[{"type":"code","lang":"python","executable":true,"value":"yd.dask","key":"go9d8NEWFu"},{"type":"outputs","id":"C_JkCCI-_v-0Q4b9PrOIA","children":[{"type":"output","children":[],"jupyter_data":{"output_type":"execute_result","execution_count":5,"metadata":{},"data":{"text/plain":{"content":"HighLevelGraph with 4 layers.\n<dask.highlevelgraph.HighLevelGraph object at 0x7ff083c64050>\n 0. normal-c502eddcd86746fed6c2c17c0a5b1a64\n 1. mean_chunk-8f04ffc306faa30f0e6961dc0bd0fe9f\n 2. mean_combine-partial-1cbd09d6e18f61d4a3e70f5a78a71f91\n 3. mean_agg-aggregate-eee9973051b6360bfbd2d56c0654ab74","content_type":"text/plain"},"text/html":{"content":"<div>\n    <div>\n        <div style=\"width: 52px; height: 52px; position: absolute;\">\n            <svg width=\"76\" height=\"71\" viewBox=\"0 0 76 71\" fill=\"none\" xmlns=\"http://www.w3.org/2000/svg\">\n                <circle cx=\"61.5\" cy=\"36.5\" r=\"13.5\" style=\"stroke: var(--jp-ui-font-color2, #1D1D1D); fill: var(--jp-layout-color1, #F2F2F2);\" stroke-width=\"2\"/>\n                <circle cx=\"14.5\" cy=\"14.5\" r=\"13.5\" style=\"stroke: var(--jp-ui-font-color2, #1D1D1D); fill: var(--jp-layout-color1, #F2F2F2);\" stroke-width=\"2\"/>\n                <circle cx=\"14.5\" cy=\"56.5\" r=\"13.5\" style=\"stroke: var(--jp-ui-font-color2, #1D1D1D); fill: var(--jp-layout-color1, #F2F2F2);\" stroke-width=\"2\"/>\n                <path d=\"M28 16L30.5 16C33.2614 16 35.5 18.2386 35.5 21L35.5 32.0001C35.5 34.7615 37.7386 37.0001 40.5 37.0001L43 37.0001\" style=\"stroke: var(--jp-ui-font-color2, #1D1D1D);\" stroke-width=\"1.5\"/>\n                <path d=\"M40.5 37L40.5 37.75L40.5 37.75L40.5 37ZM35.5 42L36.25 42L35.5 42ZM35.5 52L34.75 52L35.5 52ZM30.5 57L30.5 57.75L30.5 57ZM41.5001 36.25L40.5 36.25L40.5 37.75L41.5001 37.75L41.5001 36.25ZM34.75 42L34.75 52L36.25 52L36.25 42L34.75 42ZM30.5 56.25L28.0001 56.25L28.0001 57.75L30.5 57.75L30.5 56.25ZM34.75 52C34.75 54.3472 32.8472 56.25 30.5 56.25L30.5 57.75C33.6756 57.75 36.25 55.1756 36.25 52L34.75 52ZM40.5 36.25C37.3244 36.25 34.75 38.8243 34.75 42L36.25 42C36.25 39.6528 38.1528 37.75 40.5 37.75L40.5 36.25Z\" style=\"fill: var(--jp-ui-font-color2, #1D1D1D);\"/>\n                <circle cx=\"28\" cy=\"16\" r=\"2.25\" fill=\"#E5E5E5\" style=\"stroke: var(--jp-ui-font-color2, #1D1D1D);\" stroke-width=\"1.5\"/>\n                <circle cx=\"28\" cy=\"57\" r=\"2.25\" fill=\"#E5E5E5\" style=\"stroke: var(--jp-ui-font-color2, #1D1D1D);\" stroke-width=\"1.5\"/>\n                <path d=\"M45.25 36.567C45.5833 36.7594 45.5833 37.2406 45.25 37.433L42.25 39.1651C41.9167 39.3575 41.5 39.117 41.5 38.7321V35.2679C41.5 34.883 41.9167 34.6425 42.25 34.8349L45.25 36.567Z\" style=\"fill: var(--jp-ui-font-color2, #1D1D1D);\"/>\n            </svg>\n        </div>\n        <div style=\"margin-left: 64px;\">\n            <h3 style=\"margin-bottom: 0px;\">HighLevelGraph</h3>\n            <p style=\"color: var(--jp-ui-font-color2, #5D5851); margin-bottom:0px;\">\n                HighLevelGraph with 4 layers and 240 keys from all layers.\n            </p>\n            \n            <div style=\"\">\n    <svg width=\"24\" height=\"24\" viewBox=\"0 0 32 32\" fill=\"none\" xmlns=\"http://www.w3.org/2000/svg\" style=\"position: absolute;\">\n        \n        <circle cx=\"16\" cy=\"16\" r=\"14\" fill=\"#8F8F8F\" style=\"stroke: var(--jp-ui-font-color2, #1D1D1D);\" stroke-width=\"2\"/>\n        \n    </svg>\n\n    <details style=\"margin-left: 32px;\">\n        <summary style=\"margin-bottom: 10px; margin-top: 10px;\">\n            <h4 style=\"display: inline;\">Layer1: normal</h4>\n        </summary>\n        <p style=\"color: var(--jp-ui-font-color2, #5D5851); margin: -0.25em 0px 0px 0px;\">\n            normal-c502eddcd86746fed6c2c17c0a5b1a64\n        </p>\n\n        <table>\n        <tr>\n            <td>\n                <table>\n                \n                    <tr>\n                        <th style=\"text-align: left; width: 150px;\">layer_type</th>\n                        <td style=\"text-align: left;\">MaterializedLayer</td>\n                    </tr>\n                \n                    <tr>\n                        <th style=\"text-align: left; width: 150px;\">is_materialized</th>\n                        <td style=\"text-align: left;\">True</td>\n                    </tr>\n                \n                    <tr>\n                        <th style=\"text-align: left; width: 150px;\">number of outputs</th>\n                        <td style=\"text-align: left;\">100</td>\n                    </tr>\n                \n                    <tr>\n                        <th style=\"text-align: left; width: 150px;\">shape</th>\n                        <td style=\"text-align: left;\">(20000, 20000)</td>\n                    </tr>\n                \n                    <tr>\n                        <th style=\"text-align: left; width: 150px;\">dtype</th>\n                        <td style=\"text-align: left;\">float64</td>\n                    </tr>\n                \n                    <tr>\n                        <th style=\"text-align: left; width: 150px;\">chunksize</th>\n                        <td style=\"text-align: left;\">(2000, 2000)</td>\n                    </tr>\n                \n                    <tr>\n                        <th style=\"text-align: left; width: 150px;\">type</th>\n                        <td style=\"text-align: left;\">dask.array.core.Array</td>\n                    </tr>\n                \n                    <tr>\n                        <th style=\"text-align: left; width: 150px;\">chunk_type</th>\n                        <td style=\"text-align: left;\">numpy.ndarray</td>\n                    </tr>\n                \n                \n                </table>\n            </td>\n            <td>\n                <svg width=\"250\" height=\"250\" style=\"stroke:rgb(0,0,0);stroke-width:1\" >\n\n  <!-- Horizontal lines -->\n  <line x1=\"0\" y1=\"0\" x2=\"200\" y2=\"0\" style=\"stroke-width:2\" />\n  <line x1=\"0\" y1=\"20\" x2=\"200\" y2=\"20\" />\n  <line x1=\"0\" y1=\"40\" x2=\"200\" y2=\"40\" />\n  <line x1=\"0\" y1=\"60\" x2=\"200\" y2=\"60\" />\n  <line x1=\"0\" y1=\"80\" x2=\"200\" y2=\"80\" />\n  <line x1=\"0\" y1=\"100\" x2=\"200\" y2=\"100\" />\n  <line x1=\"0\" y1=\"120\" x2=\"200\" y2=\"120\" />\n  <line x1=\"0\" y1=\"140\" x2=\"200\" y2=\"140\" />\n  <line x1=\"0\" y1=\"160\" x2=\"200\" y2=\"160\" />\n  <line x1=\"0\" y1=\"180\" x2=\"200\" y2=\"180\" />\n  <line x1=\"0\" y1=\"200\" x2=\"200\" y2=\"200\" style=\"stroke-width:2\" />\n\n  <!-- Vertical lines -->\n  <line x1=\"0\" y1=\"0\" x2=\"0\" y2=\"200\" style=\"stroke-width:2\" />\n  <line x1=\"20\" y1=\"0\" x2=\"20\" y2=\"200\" />\n  <line x1=\"40\" y1=\"0\" x2=\"40\" y2=\"200\" />\n  <line x1=\"60\" y1=\"0\" x2=\"60\" y2=\"200\" />\n  <line x1=\"80\" y1=\"0\" x2=\"80\" y2=\"200\" />\n  <line x1=\"100\" y1=\"0\" x2=\"100\" y2=\"200\" />\n  <line x1=\"120\" y1=\"0\" x2=\"120\" y2=\"200\" />\n  <line x1=\"140\" y1=\"0\" x2=\"140\" y2=\"200\" />\n  <line x1=\"160\" y1=\"0\" x2=\"160\" y2=\"200\" />\n  <line x1=\"180\" y1=\"0\" x2=\"180\" y2=\"200\" />\n  <line x1=\"200\" y1=\"0\" x2=\"200\" y2=\"200\" style=\"stroke-width:2\" />\n\n  <!-- Colored Rectangle -->\n  <polygon points=\"0.0,0.0 200.0,0.0 200.0,200.0 0.0,200.0\" style=\"fill:#ECB172A0;stroke-width:0\"/>\n\n  <!-- Text -->\n  <text x=\"100.0\" y=\"220.0\" font-size=\"1.0rem\" font-weight=\"100\" text-anchor=\"middle\" >20000</text>\n  <text x=\"220.0\" y=\"100.0\" font-size=\"1.0rem\" font-weight=\"100\" text-anchor=\"middle\" transform=\"rotate(-90,220.0,100.0)\">20000</text>\n</svg>\n            </td>\n        </tr>\n        </table>\n\n    </details>\n</div>\n            \n            <div style=\"\">\n    <svg width=\"24\" height=\"24\" viewBox=\"0 0 32 32\" fill=\"none\" xmlns=\"http://www.w3.org/2000/svg\" style=\"position: absolute;\">\n        \n        <circle cx=\"16\" cy=\"16\" r=\"14\" fill=\"#8F8F8F\" style=\"stroke: var(--jp-ui-font-color2, #1D1D1D);\" stroke-width=\"2\"/>\n        \n    </svg>\n\n    <details style=\"margin-left: 32px;\">\n        <summary style=\"margin-bottom: 10px; margin-top: 10px;\">\n            <h4 style=\"display: inline;\">Layer2: mean_chunk</h4>\n        </summary>\n        <p style=\"color: var(--jp-ui-font-color2, #5D5851); margin: -0.25em 0px 0px 0px;\">\n            mean_chunk-8f04ffc306faa30f0e6961dc0bd0fe9f\n        </p>\n\n        <table>\n        <tr>\n            <td>\n                <table>\n                \n                    <tr>\n                        <th style=\"text-align: left; width: 150px;\">layer_type</th>\n                        <td style=\"text-align: left;\">Blockwise</td>\n                    </tr>\n                \n                    <tr>\n                        <th style=\"text-align: left; width: 150px;\">is_materialized</th>\n                        <td style=\"text-align: left;\">True</td>\n                    </tr>\n                \n                    <tr>\n                        <th style=\"text-align: left; width: 150px;\">number of outputs</th>\n                        <td style=\"text-align: left;\">100</td>\n                    </tr>\n                \n                    <tr>\n                        <th style=\"text-align: left; width: 150px;\">shape</th>\n                        <td style=\"text-align: left;\">(20000, 20000)</td>\n                    </tr>\n                \n                    <tr>\n                        <th style=\"text-align: left; width: 150px;\">dtype</th>\n                        <td style=\"text-align: left;\">float64</td>\n                    </tr>\n                \n                    <tr>\n                        <th style=\"text-align: left; width: 150px;\">chunksize</th>\n                        <td style=\"text-align: left;\">(2000, 2000)</td>\n                    </tr>\n                \n                    <tr>\n                        <th style=\"text-align: left; width: 150px;\">type</th>\n                        <td style=\"text-align: left;\">dask.array.core.Array</td>\n                    </tr>\n                \n                    <tr>\n                        <th style=\"text-align: left; width: 150px;\">chunk_type</th>\n                        <td style=\"text-align: left;\">numpy.ndarray</td>\n                    </tr>\n                \n                \n                    \n                        <tr>\n                            <th style=\"text-align: left; width: 150px;\"> depends on </th>\n                            <td style=\"text-align: left;\">normal-c502eddcd86746fed6c2c17c0a5b1a64</td>\n                        </tr>\n                    \n                \n                </table>\n            </td>\n            <td>\n                <svg width=\"250\" height=\"250\" style=\"stroke:rgb(0,0,0);stroke-width:1\" >\n\n  <!-- Horizontal lines -->\n  <line x1=\"0\" y1=\"0\" x2=\"200\" y2=\"0\" style=\"stroke-width:2\" />\n  <line x1=\"0\" y1=\"20\" x2=\"200\" y2=\"20\" />\n  <line x1=\"0\" y1=\"40\" x2=\"200\" y2=\"40\" />\n  <line x1=\"0\" y1=\"60\" x2=\"200\" y2=\"60\" />\n  <line x1=\"0\" y1=\"80\" x2=\"200\" y2=\"80\" />\n  <line x1=\"0\" y1=\"100\" x2=\"200\" y2=\"100\" />\n  <line x1=\"0\" y1=\"120\" x2=\"200\" y2=\"120\" />\n  <line x1=\"0\" y1=\"140\" x2=\"200\" y2=\"140\" />\n  <line x1=\"0\" y1=\"160\" x2=\"200\" y2=\"160\" />\n  <line x1=\"0\" y1=\"180\" x2=\"200\" y2=\"180\" />\n  <line x1=\"0\" y1=\"200\" x2=\"200\" y2=\"200\" style=\"stroke-width:2\" />\n\n  <!-- Vertical lines -->\n  <line x1=\"0\" y1=\"0\" x2=\"0\" y2=\"200\" style=\"stroke-width:2\" />\n  <line x1=\"20\" y1=\"0\" x2=\"20\" y2=\"200\" />\n  <line x1=\"40\" y1=\"0\" x2=\"40\" y2=\"200\" />\n  <line x1=\"60\" y1=\"0\" x2=\"60\" y2=\"200\" />\n  <line x1=\"80\" y1=\"0\" x2=\"80\" y2=\"200\" />\n  <line x1=\"100\" y1=\"0\" x2=\"100\" y2=\"200\" />\n  <line x1=\"120\" y1=\"0\" x2=\"120\" y2=\"200\" />\n  <line x1=\"140\" y1=\"0\" x2=\"140\" y2=\"200\" />\n  <line x1=\"160\" y1=\"0\" x2=\"160\" y2=\"200\" />\n  <line x1=\"180\" y1=\"0\" x2=\"180\" y2=\"200\" />\n  <line x1=\"200\" y1=\"0\" x2=\"200\" y2=\"200\" style=\"stroke-width:2\" />\n\n  <!-- Colored Rectangle -->\n  <polygon points=\"0.0,0.0 200.0,0.0 200.0,200.0 0.0,200.0\" style=\"fill:#ECB172A0;stroke-width:0\"/>\n\n  <!-- Text -->\n  <text x=\"100.0\" y=\"220.0\" font-size=\"1.0rem\" font-weight=\"100\" text-anchor=\"middle\" >20000</text>\n  <text x=\"220.0\" y=\"100.0\" font-size=\"1.0rem\" font-weight=\"100\" text-anchor=\"middle\" transform=\"rotate(-90,220.0,100.0)\">20000</text>\n</svg>\n            </td>\n        </tr>\n        </table>\n\n    </details>\n</div>\n            \n            <div style=\"\">\n    <svg width=\"24\" height=\"24\" viewBox=\"0 0 32 32\" fill=\"none\" xmlns=\"http://www.w3.org/2000/svg\" style=\"position: absolute;\">\n        \n        <circle cx=\"16\" cy=\"16\" r=\"14\" fill=\"#8F8F8F\" style=\"stroke: var(--jp-ui-font-color2, #1D1D1D);\" stroke-width=\"2\"/>\n        \n    </svg>\n\n    <details style=\"margin-left: 32px;\">\n        <summary style=\"margin-bottom: 10px; margin-top: 10px;\">\n            <h4 style=\"display: inline;\">Layer3: mean_combine-partial</h4>\n        </summary>\n        <p style=\"color: var(--jp-ui-font-color2, #5D5851); margin: -0.25em 0px 0px 0px;\">\n            mean_combine-partial-1cbd09d6e18f61d4a3e70f5a78a71f91\n        </p>\n\n        <table>\n        <tr>\n            <td>\n                <table>\n                \n                    <tr>\n                        <th style=\"text-align: left; width: 150px;\">layer_type</th>\n                        <td style=\"text-align: left;\">MaterializedLayer</td>\n                    </tr>\n                \n                    <tr>\n                        <th style=\"text-align: left; width: 150px;\">is_materialized</th>\n                        <td style=\"text-align: left;\">True</td>\n                    </tr>\n                \n                    <tr>\n                        <th style=\"text-align: left; width: 150px;\">number of outputs</th>\n                        <td style=\"text-align: left;\">30</td>\n                    </tr>\n                \n                    <tr>\n                        <th style=\"text-align: left; width: 150px;\">shape</th>\n                        <td style=\"text-align: left;\">(3, 20000)</td>\n                    </tr>\n                \n                    <tr>\n                        <th style=\"text-align: left; width: 150px;\">dtype</th>\n                        <td style=\"text-align: left;\">float64</td>\n                    </tr>\n                \n                    <tr>\n                        <th style=\"text-align: left; width: 150px;\">chunksize</th>\n                        <td style=\"text-align: left;\">(1, 2000)</td>\n                    </tr>\n                \n                    <tr>\n                        <th style=\"text-align: left; width: 150px;\">type</th>\n                        <td style=\"text-align: left;\">dask.array.core.Array</td>\n                    </tr>\n                \n                    <tr>\n                        <th style=\"text-align: left; width: 150px;\">chunk_type</th>\n                        <td style=\"text-align: left;\">numpy.ndarray</td>\n                    </tr>\n                \n                \n                    \n                        <tr>\n                            <th style=\"text-align: left; width: 150px;\"> depends on </th>\n                            <td style=\"text-align: left;\">mean_chunk-8f04ffc306faa30f0e6961dc0bd0fe9f</td>\n                        </tr>\n                    \n                \n                </table>\n            </td>\n            <td>\n                <svg width=\"250\" height=\"92\" style=\"stroke:rgb(0,0,0);stroke-width:1\" >\n\n  <!-- Horizontal lines -->\n  <line x1=\"0\" y1=\"0\" x2=\"200\" y2=\"0\" style=\"stroke-width:2\" />\n  <line x1=\"0\" y1=\"14\" x2=\"200\" y2=\"14\" />\n  <line x1=\"0\" y1=\"28\" x2=\"200\" y2=\"28\" />\n  <line x1=\"0\" y1=\"42\" x2=\"200\" y2=\"42\" style=\"stroke-width:2\" />\n\n  <!-- Vertical lines -->\n  <line x1=\"0\" y1=\"0\" x2=\"0\" y2=\"42\" style=\"stroke-width:2\" />\n  <line x1=\"20\" y1=\"0\" x2=\"20\" y2=\"42\" />\n  <line x1=\"40\" y1=\"0\" x2=\"40\" y2=\"42\" />\n  <line x1=\"60\" y1=\"0\" x2=\"60\" y2=\"42\" />\n  <line x1=\"80\" y1=\"0\" x2=\"80\" y2=\"42\" />\n  <line x1=\"100\" y1=\"0\" x2=\"100\" y2=\"42\" />\n  <line x1=\"120\" y1=\"0\" x2=\"120\" y2=\"42\" />\n  <line x1=\"140\" y1=\"0\" x2=\"140\" y2=\"42\" />\n  <line x1=\"160\" y1=\"0\" x2=\"160\" y2=\"42\" />\n  <line x1=\"180\" y1=\"0\" x2=\"180\" y2=\"42\" />\n  <line x1=\"200\" y1=\"0\" x2=\"200\" y2=\"42\" style=\"stroke-width:2\" />\n\n  <!-- Colored Rectangle -->\n  <polygon points=\"0.0,0.0 200.0,0.0 200.0,42.354360857637474 0.0,42.354360857637474\" style=\"fill:#ECB172A0;stroke-width:0\"/>\n\n  <!-- Text -->\n  <text x=\"100.0\" y=\"62.354360857637474\" font-size=\"1.0rem\" font-weight=\"100\" text-anchor=\"middle\" >20000</text>\n  <text x=\"220.0\" y=\"21.177180428818737\" font-size=\"1.0rem\" font-weight=\"100\" text-anchor=\"middle\" transform=\"rotate(0,220.0,21.177180428818737)\">3</text>\n</svg>\n            </td>\n        </tr>\n        </table>\n\n    </details>\n</div>\n            \n            <div style=\"\">\n    <svg width=\"24\" height=\"24\" viewBox=\"0 0 32 32\" fill=\"none\" xmlns=\"http://www.w3.org/2000/svg\" style=\"position: absolute;\">\n        \n        <circle cx=\"16\" cy=\"16\" r=\"14\" fill=\"#8F8F8F\" style=\"stroke: var(--jp-ui-font-color2, #1D1D1D);\" stroke-width=\"2\"/>\n        \n    </svg>\n\n    <details style=\"margin-left: 32px;\">\n        <summary style=\"margin-bottom: 10px; margin-top: 10px;\">\n            <h4 style=\"display: inline;\">Layer4: mean_agg-aggregate</h4>\n        </summary>\n        <p style=\"color: var(--jp-ui-font-color2, #5D5851); margin: -0.25em 0px 0px 0px;\">\n            mean_agg-aggregate-eee9973051b6360bfbd2d56c0654ab74\n        </p>\n\n        <table>\n        <tr>\n            <td>\n                <table>\n                \n                    <tr>\n                        <th style=\"text-align: left; width: 150px;\">layer_type</th>\n                        <td style=\"text-align: left;\">MaterializedLayer</td>\n                    </tr>\n                \n                    <tr>\n                        <th style=\"text-align: left; width: 150px;\">is_materialized</th>\n                        <td style=\"text-align: left;\">True</td>\n                    </tr>\n                \n                    <tr>\n                        <th style=\"text-align: left; width: 150px;\">number of outputs</th>\n                        <td style=\"text-align: left;\">10</td>\n                    </tr>\n                \n                    <tr>\n                        <th style=\"text-align: left; width: 150px;\">shape</th>\n                        <td style=\"text-align: left;\">(20000,)</td>\n                    </tr>\n                \n                    <tr>\n                        <th style=\"text-align: left; width: 150px;\">dtype</th>\n                        <td style=\"text-align: left;\">float64</td>\n                    </tr>\n                \n                    <tr>\n                        <th style=\"text-align: left; width: 150px;\">chunksize</th>\n                        <td style=\"text-align: left;\">(2000,)</td>\n                    </tr>\n                \n                    <tr>\n                        <th style=\"text-align: left; width: 150px;\">type</th>\n                        <td style=\"text-align: left;\">dask.array.core.Array</td>\n                    </tr>\n                \n                    <tr>\n                        <th style=\"text-align: left; width: 150px;\">chunk_type</th>\n                        <td style=\"text-align: left;\">numpy.ndarray</td>\n                    </tr>\n                \n                \n                    \n                        <tr>\n                            <th style=\"text-align: left; width: 150px;\"> depends on </th>\n                            <td style=\"text-align: left;\">mean_combine-partial-1cbd09d6e18f61d4a3e70f5a78a71f91</td>\n                        </tr>\n                    \n                \n                </table>\n            </td>\n            <td>\n                <svg width=\"250\" height=\"92\" style=\"stroke:rgb(0,0,0);stroke-width:1\" >\n\n  <!-- Horizontal lines -->\n  <line x1=\"0\" y1=\"0\" x2=\"200\" y2=\"0\" style=\"stroke-width:2\" />\n  <line x1=\"0\" y1=\"42\" x2=\"200\" y2=\"42\" style=\"stroke-width:2\" />\n\n  <!-- Vertical lines -->\n  <line x1=\"0\" y1=\"0\" x2=\"0\" y2=\"42\" style=\"stroke-width:2\" />\n  <line x1=\"20\" y1=\"0\" x2=\"20\" y2=\"42\" />\n  <line x1=\"40\" y1=\"0\" x2=\"40\" y2=\"42\" />\n  <line x1=\"60\" y1=\"0\" x2=\"60\" y2=\"42\" />\n  <line x1=\"80\" y1=\"0\" x2=\"80\" y2=\"42\" />\n  <line x1=\"100\" y1=\"0\" x2=\"100\" y2=\"42\" />\n  <line x1=\"120\" y1=\"0\" x2=\"120\" y2=\"42\" />\n  <line x1=\"140\" y1=\"0\" x2=\"140\" y2=\"42\" />\n  <line x1=\"160\" y1=\"0\" x2=\"160\" y2=\"42\" />\n  <line x1=\"180\" y1=\"0\" x2=\"180\" y2=\"42\" />\n  <line x1=\"200\" y1=\"0\" x2=\"200\" y2=\"42\" style=\"stroke-width:2\" />\n\n  <!-- Colored Rectangle -->\n  <polygon points=\"0.0,0.0 200.0,0.0 200.0,42.354360857637474 0.0,42.354360857637474\" style=\"fill:#ECB172A0;stroke-width:0\"/>\n\n  <!-- Text -->\n  <text x=\"100.0\" y=\"62.354360857637474\" font-size=\"1.0rem\" font-weight=\"100\" text-anchor=\"middle\" >20000</text>\n  <text x=\"220.0\" y=\"21.177180428818737\" font-size=\"1.0rem\" font-weight=\"100\" text-anchor=\"middle\" transform=\"rotate(0,220.0,21.177180428818737)\">1</text>\n</svg>\n            </td>\n        </tr>\n        </table>\n\n    </details>\n</div>\n            \n        </div>\n    </div>\n</div>","content_type":"text/html"}}},"key":"IPFJofWGX7"}],"key":"uvk6FfHJPd"}],"key":"T8Ootpsa8C"},{"type":"block","kind":"notebook-code","children":[{"type":"code","lang":"python","executable":true,"value":"yd","key":"Qz7nbbfAMd"},{"type":"outputs","id":"MPUwabyay7dpOOIk5hLjd","children":[{"type":"output","children":[],"jupyter_data":{"output_type":"execute_result","execution_count":6,"metadata":{},"data":{"text/plain":{"content":"dask.array<mean_agg-aggregate, shape=(20000,), dtype=float64, chunksize=(2000,), chunktype=numpy.ndarray>","content_type":"text/plain"},"text/html":{"content":"<table>\n    <tr>\n        <td>\n            <table style=\"border-collapse: collapse;\">\n                <thead>\n                    <tr>\n                        <td> </td>\n                        <th> Array </th>\n                        <th> Chunk </th>\n                    </tr>\n                </thead>\n                <tbody>\n                    \n                    <tr>\n                        <th> Bytes </th>\n                        <td> 156.25 kiB </td>\n                        <td> 15.62 kiB </td>\n                    </tr>\n                    \n                    <tr>\n                        <th> Shape </th>\n                        <td> (20000,) </td>\n                        <td> (2000,) </td>\n                    </tr>\n                    <tr>\n                        <th> Dask graph </th>\n                        <td colspan=\"2\"> 10 chunks in 4 graph layers </td>\n                    </tr>\n                    <tr>\n                        <th> Data type </th>\n                        <td colspan=\"2\"> float64 numpy.ndarray </td>\n                    </tr>\n                </tbody>\n            </table>\n        </td>\n        <td>\n        <svg width=\"170\" height=\"75\" style=\"stroke:rgb(0,0,0);stroke-width:1\" >\n\n  <!-- Horizontal lines -->\n  <line x1=\"0\" y1=\"0\" x2=\"120\" y2=\"0\" style=\"stroke-width:2\" />\n  <line x1=\"0\" y1=\"25\" x2=\"120\" y2=\"25\" style=\"stroke-width:2\" />\n\n  <!-- Vertical lines -->\n  <line x1=\"0\" y1=\"0\" x2=\"0\" y2=\"25\" style=\"stroke-width:2\" />\n  <line x1=\"12\" y1=\"0\" x2=\"12\" y2=\"25\" />\n  <line x1=\"24\" y1=\"0\" x2=\"24\" y2=\"25\" />\n  <line x1=\"36\" y1=\"0\" x2=\"36\" y2=\"25\" />\n  <line x1=\"48\" y1=\"0\" x2=\"48\" y2=\"25\" />\n  <line x1=\"60\" y1=\"0\" x2=\"60\" y2=\"25\" />\n  <line x1=\"72\" y1=\"0\" x2=\"72\" y2=\"25\" />\n  <line x1=\"84\" y1=\"0\" x2=\"84\" y2=\"25\" />\n  <line x1=\"96\" y1=\"0\" x2=\"96\" y2=\"25\" />\n  <line x1=\"108\" y1=\"0\" x2=\"108\" y2=\"25\" />\n  <line x1=\"120\" y1=\"0\" x2=\"120\" y2=\"25\" style=\"stroke-width:2\" />\n\n  <!-- Colored Rectangle -->\n  <polygon points=\"0.0,0.0 120.0,0.0 120.0,25.412616514582485 0.0,25.412616514582485\" style=\"fill:#ECB172A0;stroke-width:0\"/>\n\n  <!-- Text -->\n  <text x=\"60.0\" y=\"45.41261651458248\" font-size=\"1.0rem\" font-weight=\"100\" text-anchor=\"middle\" >20000</text>\n  <text x=\"140.0\" y=\"12.706308257291242\" font-size=\"1.0rem\" font-weight=\"100\" text-anchor=\"middle\" transform=\"rotate(0,140.0,12.706308257291242)\">1</text>\n</svg>\n        </td>\n    </tr>\n</table>","content_type":"text/html"}}},"key":"vDbQ0paStx"}],"key":"P9wJMHOcH9"}],"key":"ImGyPwGkuD"},{"type":"block","kind":"notebook-content","children":[{"type":"list","ordered":false,"spread":false,"position":{"start":{"line":1,"column":1},"end":{"line":3,"column":1}},"children":[{"type":"listItem","spread":true,"position":{"start":{"line":1,"column":1},"end":{"line":1,"column":1}},"children":[{"type":"paragraph","children":[{"type":"text","value":"Notice how ","position":{"start":{"line":1,"column":1},"end":{"line":1,"column":1}},"key":"zmyxuRkb3N"},{"type":"inlineCode","value":"sync","position":{"start":{"line":1,"column":1},"end":{"line":1,"column":1}},"key":"CaV3g6azgc"},{"type":"text","value":" scheduler takes almost the same time as pure NumPy code.","position":{"start":{"line":1,"column":1},"end":{"line":1,"column":1}},"key":"eaGMDfdAM2"}],"key":"bv6y0UceCH"}],"key":"G0SrfXtw5m"},{"type":"listItem","spread":true,"position":{"start":{"line":2,"column":1},"end":{"line":3,"column":1}},"children":[{"type":"paragraph","children":[{"type":"text","value":"Why is the multiprocessing scheduler so much slower?","position":{"start":{"line":2,"column":1},"end":{"line":2,"column":1}},"key":"NIgk2EYei0"}],"key":"VEL2Fjyl4e"}],"key":"aD1OhlnVch"}],"key":"YlMZql1uMj"},{"type":"paragraph","position":{"start":{"line":4,"column":1},"end":{"line":4,"column":1}},"children":[{"type":"text","value":"If you use the multiprocessing backend, all communication between processes still needs to pass through the main process because processes are isolated from other processes. This introduces a large overhead.","position":{"start":{"line":4,"column":1},"end":{"line":4,"column":1}},"key":"chKODWfyQB"}],"key":"MeRJlZ3eVv"},{"type":"paragraph","position":{"start":{"line":6,"column":1},"end":{"line":6,"column":1}},"children":[{"type":"strong","position":{"start":{"line":6,"column":1},"end":{"line":6,"column":1}},"children":[{"type":"text","value":"The Dask developers recommend using the Dask Distributed Scheduler which we will cover now.","position":{"start":{"line":6,"column":1},"end":{"line":6,"column":1}},"key":"KvvQjw5Cr7"}],"key":"BUHkTV7Stc"}],"key":"vMhAGJZc1q"}],"key":"hHg7Swb0gF"},{"type":"block","kind":"notebook-content","children":[{"type":"heading","depth":3,"position":{"start":{"line":2,"column":1},"end":{"line":2,"column":1}},"children":[{"type":"text","value":"2. Distributed scheduler","position":{"start":{"line":2,"column":1},"end":{"line":2,"column":1}},"key":"s9cBIqjjNy"}],"identifier":"id-2-distributed-scheduler","label":"2. Distributed scheduler","html_id":"id-2-distributed-scheduler","implicit":true,"key":"kHa847ZTW4"},{"type":"list","ordered":false,"spread":false,"position":{"start":{"line":3,"column":1},"end":{"line":6,"column":1}},"children":[{"type":"listItem","spread":true,"position":{"start":{"line":3,"column":1},"end":{"line":3,"column":1}},"children":[{"type":"paragraph","children":[{"type":"text","value":"The Distributed scheduler or ","position":{"start":{"line":3,"column":1},"end":{"line":3,"column":1}},"key":"pzRL8MK5Qp"},{"type":"inlineCode","value":"dask.distributed","position":{"start":{"line":3,"column":1},"end":{"line":3,"column":1}},"key":"MWxTGKv9g1"},{"type":"text","value":" schedules tasks and manages the execution of those tasks on workers from a single or multiple machines.","position":{"start":{"line":3,"column":1},"end":{"line":3,"column":1}},"key":"HsjMIYBrL7"}],"key":"EYqBvG7Qv4"}],"key":"bTxjK0zjA5"},{"type":"listItem","spread":true,"position":{"start":{"line":4,"column":1},"end":{"line":6,"column":1}},"children":[{"type":"paragraph","children":[{"type":"text","value":"This scheduler is more sophisticated and offers more features including a live diagnostic dashboard which provides live insight on performance and progress of the calculations.","position":{"start":{"line":4,"column":1},"end":{"line":4,"column":1}},"key":"fMfKljY9Tt"}],"key":"AwrqHHlPNp"}],"key":"Ku8ofPGeFD"}],"key":"R4HjMHwQfK"},{"type":"paragraph","position":{"start":{"line":7,"column":1},"end":{"line":7,"column":1}},"children":[{"type":"text","value":"In most cases, ","position":{"start":{"line":7,"column":1},"end":{"line":7,"column":1}},"key":"uUWvl0lXqh"},{"type":"inlineCode","value":"dask.distributed","position":{"start":{"line":7,"column":1},"end":{"line":7,"column":1}},"key":"mHrQvmLO8n"},{"type":"text","value":" is preferred since it is very scalable, and provides and informative interactive dashboard and access to more complex Dask collections such as ","position":{"start":{"line":7,"column":1},"end":{"line":7,"column":1}},"key":"PorafBXi4V"},{"type":"inlineCode","value":"futures","position":{"start":{"line":7,"column":1},"end":{"line":7,"column":1}},"key":"eru0Dm4scC"},{"type":"text","value":".","position":{"start":{"line":7,"column":1},"end":{"line":7,"column":1}},"key":"SzIW6eQyGu"}],"key":"QmQcjmEefu"}],"key":"ssoKT6xwAJ"},{"type":"block","kind":"notebook-content","children":[{"type":"heading","depth":4,"position":{"start":{"line":1,"column":1},"end":{"line":1,"column":1}},"children":[{"type":"text","value":"2.1. Local Cluster","position":{"start":{"line":1,"column":1},"end":{"line":1,"column":1}},"key":"o0eIL8dsHS"}],"identifier":"id-2-1-local-cluster","label":"2.1. Local Cluster","html_id":"id-2-1-local-cluster","implicit":true,"key":"xD7BJZwNjG"},{"type":"paragraph","position":{"start":{"line":3,"column":1},"end":{"line":3,"column":1}},"children":[{"type":"text","value":"A Dask Local Cluster refers to a group of worker processes that run on a single machine and are managed by a single Dask scheduler.","position":{"start":{"line":3,"column":1},"end":{"line":3,"column":1}},"key":"izWdDenxfE"}],"key":"UjgSKoAHwO"},{"type":"paragraph","position":{"start":{"line":5,"column":1},"end":{"line":5,"column":1}},"children":[{"type":"text","value":"This is useful for situations where the computational requirements are not large enough to warrant the use of a full cluster of separate machines. It provides an easy way to run parallel computations on a single machine, without the need for complex cluster management or other infrastructure.","position":{"start":{"line":5,"column":1},"end":{"line":5,"column":1}},"key":"ezG291wLVV"}],"key":"Ttb8vnI6y7"}],"key":"AYqsgsCfqk"},{"type":"block","kind":"notebook-content","children":[{"type":"heading","depth":5,"position":{"start":{"line":1,"column":1},"end":{"line":1,"column":1}},"children":[{"type":"text","value":"Let’s start by creating a Local Cluster","position":{"start":{"line":1,"column":1},"end":{"line":1,"column":1}},"key":"Ywg9UYmF99"}],"identifier":"lets-start-by-creating-a-local-cluster","label":"Let’s start by creating a Local Cluster","html_id":"lets-start-by-creating-a-local-cluster","implicit":true,"key":"oGXLMR5q3e"},{"type":"paragraph","position":{"start":{"line":3,"column":1},"end":{"line":3,"column":1}},"children":[{"type":"text","value":"For this we need to set up a ","position":{"start":{"line":3,"column":1},"end":{"line":3,"column":1}},"key":"yZglY9e6Xo"},{"type":"inlineCode","value":"LocalCluster","position":{"start":{"line":3,"column":1},"end":{"line":3,"column":1}},"key":"GzI5dYGkBQ"},{"type":"text","value":" using ","position":{"start":{"line":3,"column":1},"end":{"line":3,"column":1}},"key":"B1RsH3c3oL"},{"type":"inlineCode","value":"dask.distributed","position":{"start":{"line":3,"column":1},"end":{"line":3,"column":1}},"key":"unpwIEy1At"},{"type":"text","value":" and connect a ","position":{"start":{"line":3,"column":1},"end":{"line":3,"column":1}},"key":"xInWzZd4Me"},{"type":"inlineCode","value":"client","position":{"start":{"line":3,"column":1},"end":{"line":3,"column":1}},"key":"A5dfJruRa6"},{"type":"text","value":" to it.","position":{"start":{"line":3,"column":1},"end":{"line":3,"column":1}},"key":"uLwxt2C4bx"}],"key":"Wj3wpBcmfj"}],"key":"kLIErgi7oc"},{"type":"block","kind":"notebook-code","children":[{"type":"code","lang":"python","executable":true,"value":"from dask.distributed import LocalCluster, Client\n\ncluster = LocalCluster()\nclient = Client(cluster)\nclient","key":"QdYy0QWgmJ"},{"type":"outputs","id":"ug1lq4WH1L8s8C94S2SmX","children":[{"type":"output","children":[],"jupyter_data":{"output_type":"stream","name":"stderr","text":"/home/runner/micromamba/envs/dask-cookbook/lib/python3.14/site-packages/distributed/node.py:188: UserWarning: Port 8787 is already in use.\nPerhaps you already have a cluster running?\nHosting the HTTP server on port 33905 instead\n  warnings.warn(\n"},"key":"XyQvX9rNcN"},{"type":"output","children":[],"jupyter_data":{"output_type":"execute_result","execution_count":7,"metadata":{},"data":{"text/plain":{"content":"<Client: 'tcp://127.0.0.1:35397' processes=4 threads=4, memory=15.62 GiB>","content_type":"text/plain"},"text/html":{"content":"<div>\n    <div style=\"width: 24px; height: 24px; background-color: #e1e1e1; border: 3px solid #9D9D9D; border-radius: 5px; position: absolute;\"> </div>\n    <div style=\"margin-left: 48px;\">\n        <h3 style=\"margin-bottom: 0px;\">Client</h3>\n        <p style=\"color: #9D9D9D; margin-bottom: 0px;\">Client-81cb5843-1726-11f1-9069-7ced8d6e4526</p>\n        <table style=\"width: 100%; text-align: left;\">\n\n        <tr>\n        \n            <td style=\"text-align: left;\"><strong>Connection method:</strong> Cluster object</td>\n            <td style=\"text-align: left;\"><strong>Cluster type:</strong> distributed.LocalCluster</td>\n        \n        </tr>\n\n        \n            <tr>\n                <td style=\"text-align: left;\">\n                    <strong>Dashboard: </strong> <a href=\"http://127.0.0.1:33905/status\" target=\"_blank\">http://127.0.0.1:33905/status</a>\n                </td>\n                <td style=\"text-align: left;\"></td>\n            </tr>\n        \n\n        </table>\n\n        \n            <button style=\"margin-bottom: 12px;\" data-commandlinker-command=\"dask:populate-and-launch-layout\" data-commandlinker-args='{\"url\": \"http://127.0.0.1:33905/status\" }'>\n                Launch dashboard in JupyterLab\n            </button>\n        \n\n        \n            <details>\n            <summary style=\"margin-bottom: 20px;\"><h3 style=\"display: inline;\">Cluster Info</h3></summary>\n            <div class=\"jp-RenderedHTMLCommon jp-RenderedHTML jp-mod-trusted jp-OutputArea-output\">\n    <div style=\"width: 24px; height: 24px; background-color: #e1e1e1; border: 3px solid #9D9D9D; border-radius: 5px; position: absolute;\">\n    </div>\n    <div style=\"margin-left: 48px;\">\n        <h3 style=\"margin-bottom: 0px; margin-top: 0px;\">LocalCluster</h3>\n        <p style=\"color: #9D9D9D; margin-bottom: 0px;\">d6da7015</p>\n        <table style=\"width: 100%; text-align: left;\">\n            <tr>\n                <td style=\"text-align: left;\">\n                    <strong>Dashboard:</strong> <a href=\"http://127.0.0.1:33905/status\" target=\"_blank\">http://127.0.0.1:33905/status</a>\n                </td>\n                <td style=\"text-align: left;\">\n                    <strong>Workers:</strong> 4\n                </td>\n            </tr>\n            <tr>\n                <td style=\"text-align: left;\">\n                    <strong>Total threads:</strong> 4\n                </td>\n                <td style=\"text-align: left;\">\n                    <strong>Total memory:</strong> 15.62 GiB\n                </td>\n            </tr>\n            \n            <tr>\n    <td style=\"text-align: left;\"><strong>Status:</strong> running</td>\n    <td style=\"text-align: left;\"><strong>Using processes:</strong> True</td>\n</tr>\n\n            \n        </table>\n\n        <details>\n            <summary style=\"margin-bottom: 20px;\">\n                <h3 style=\"display: inline;\">Scheduler Info</h3>\n            </summary>\n\n            <div style=\"\">\n    <div>\n        <div style=\"width: 24px; height: 24px; background-color: #FFF7E5; border: 3px solid #FF6132; border-radius: 5px; position: absolute;\"> </div>\n        <div style=\"margin-left: 48px;\">\n            <h3 style=\"margin-bottom: 0px;\">Scheduler</h3>\n            <p style=\"color: #9D9D9D; margin-bottom: 0px;\">Scheduler-e05361ac-4877-4c2e-91f3-155845651543</p>\n            <table style=\"width: 100%; text-align: left;\">\n                <tr>\n                    <td style=\"text-align: left;\">\n                        <strong>Comm:</strong> tcp://127.0.0.1:35397\n                    </td>\n                    <td style=\"text-align: left;\">\n                        <strong>Workers:</strong> 0 \n                    </td>\n                </tr>\n                <tr>\n                    <td style=\"text-align: left;\">\n                        <strong>Dashboard:</strong> <a href=\"http://127.0.0.1:33905/status\" target=\"_blank\">http://127.0.0.1:33905/status</a>\n                    </td>\n                    <td style=\"text-align: left;\">\n                        <strong>Total threads:</strong> 0\n                    </td>\n                </tr>\n                <tr>\n                    <td style=\"text-align: left;\">\n                        <strong>Started:</strong> Just now\n                    </td>\n                    <td style=\"text-align: left;\">\n                        <strong>Total memory:</strong> 0 B\n                    </td>\n                </tr>\n            </table>\n        </div>\n    </div>\n\n    <details style=\"margin-left: 48px;\">\n        <summary style=\"margin-bottom: 20px;\">\n            <h3 style=\"display: inline;\">Workers</h3>\n        </summary>\n\n        \n        <div style=\"margin-bottom: 20px;\">\n            <div style=\"width: 24px; height: 24px; background-color: #DBF5FF; border: 3px solid #4CC9FF; border-radius: 5px; position: absolute;\"> </div>\n            <div style=\"margin-left: 48px;\">\n            <details>\n                <summary>\n                    <h4 style=\"margin-bottom: 0px; display: inline;\">Worker: 0</h4>\n                </summary>\n                <table style=\"width: 100%; text-align: left;\">\n                    <tr>\n                        <td style=\"text-align: left;\">\n                            <strong>Comm: </strong> tcp://127.0.0.1:39915\n                        </td>\n                        <td style=\"text-align: left;\">\n                            <strong>Total threads: </strong> 1\n                        </td>\n                    </tr>\n                    <tr>\n                        <td style=\"text-align: left;\">\n                            <strong>Dashboard: </strong> <a href=\"http://127.0.0.1:36587/status\" target=\"_blank\">http://127.0.0.1:36587/status</a>\n                        </td>\n                        <td style=\"text-align: left;\">\n                            <strong>Memory: </strong> 3.90 GiB\n                        </td>\n                    </tr>\n                    <tr>\n                        <td style=\"text-align: left;\">\n                            <strong>Nanny: </strong> tcp://127.0.0.1:38647\n                        </td>\n                        <td style=\"text-align: left;\"></td>\n                    </tr>\n                    <tr>\n                        <td colspan=\"2\" style=\"text-align: left;\">\n                            <strong>Local directory: </strong> /tmp/dask-scratch-space/worker-lw437z94\n                        </td>\n                    </tr>\n\n                    \n\n                    \n\n                </table>\n            </details>\n            </div>\n        </div>\n        \n        <div style=\"margin-bottom: 20px;\">\n            <div style=\"width: 24px; height: 24px; background-color: #DBF5FF; border: 3px solid #4CC9FF; border-radius: 5px; position: absolute;\"> </div>\n            <div style=\"margin-left: 48px;\">\n            <details>\n                <summary>\n                    <h4 style=\"margin-bottom: 0px; display: inline;\">Worker: 1</h4>\n                </summary>\n                <table style=\"width: 100%; text-align: left;\">\n                    <tr>\n                        <td style=\"text-align: left;\">\n                            <strong>Comm: </strong> tcp://127.0.0.1:45203\n                        </td>\n                        <td style=\"text-align: left;\">\n                            <strong>Total threads: </strong> 1\n                        </td>\n                    </tr>\n                    <tr>\n                        <td style=\"text-align: left;\">\n                            <strong>Dashboard: </strong> <a href=\"http://127.0.0.1:41771/status\" target=\"_blank\">http://127.0.0.1:41771/status</a>\n                        </td>\n                        <td style=\"text-align: left;\">\n                            <strong>Memory: </strong> 3.90 GiB\n                        </td>\n                    </tr>\n                    <tr>\n                        <td style=\"text-align: left;\">\n                            <strong>Nanny: </strong> tcp://127.0.0.1:34653\n                        </td>\n                        <td style=\"text-align: left;\"></td>\n                    </tr>\n                    <tr>\n                        <td colspan=\"2\" style=\"text-align: left;\">\n                            <strong>Local directory: </strong> /tmp/dask-scratch-space/worker-s_69hze2\n                        </td>\n                    </tr>\n\n                    \n\n                    \n\n                </table>\n            </details>\n            </div>\n        </div>\n        \n        <div style=\"margin-bottom: 20px;\">\n            <div style=\"width: 24px; height: 24px; background-color: #DBF5FF; border: 3px solid #4CC9FF; border-radius: 5px; position: absolute;\"> </div>\n            <div style=\"margin-left: 48px;\">\n            <details>\n                <summary>\n                    <h4 style=\"margin-bottom: 0px; display: inline;\">Worker: 2</h4>\n                </summary>\n                <table style=\"width: 100%; text-align: left;\">\n                    <tr>\n                        <td style=\"text-align: left;\">\n                            <strong>Comm: </strong> tcp://127.0.0.1:37925\n                        </td>\n                        <td style=\"text-align: left;\">\n                            <strong>Total threads: </strong> 1\n                        </td>\n                    </tr>\n                    <tr>\n                        <td style=\"text-align: left;\">\n                            <strong>Dashboard: </strong> <a href=\"http://127.0.0.1:45299/status\" target=\"_blank\">http://127.0.0.1:45299/status</a>\n                        </td>\n                        <td style=\"text-align: left;\">\n                            <strong>Memory: </strong> 3.90 GiB\n                        </td>\n                    </tr>\n                    <tr>\n                        <td style=\"text-align: left;\">\n                            <strong>Nanny: </strong> tcp://127.0.0.1:41295\n                        </td>\n                        <td style=\"text-align: left;\"></td>\n                    </tr>\n                    <tr>\n                        <td colspan=\"2\" style=\"text-align: left;\">\n                            <strong>Local directory: </strong> /tmp/dask-scratch-space/worker-et536ibv\n                        </td>\n                    </tr>\n\n                    \n\n                    \n\n                </table>\n            </details>\n            </div>\n        </div>\n        \n        <div style=\"margin-bottom: 20px;\">\n            <div style=\"width: 24px; height: 24px; background-color: #DBF5FF; border: 3px solid #4CC9FF; border-radius: 5px; position: absolute;\"> </div>\n            <div style=\"margin-left: 48px;\">\n            <details>\n                <summary>\n                    <h4 style=\"margin-bottom: 0px; display: inline;\">Worker: 3</h4>\n                </summary>\n                <table style=\"width: 100%; text-align: left;\">\n                    <tr>\n                        <td style=\"text-align: left;\">\n                            <strong>Comm: </strong> tcp://127.0.0.1:38671\n                        </td>\n                        <td style=\"text-align: left;\">\n                            <strong>Total threads: </strong> 1\n                        </td>\n                    </tr>\n                    <tr>\n                        <td style=\"text-align: left;\">\n                            <strong>Dashboard: </strong> <a href=\"http://127.0.0.1:35811/status\" target=\"_blank\">http://127.0.0.1:35811/status</a>\n                        </td>\n                        <td style=\"text-align: left;\">\n                            <strong>Memory: </strong> 3.90 GiB\n                        </td>\n                    </tr>\n                    <tr>\n                        <td style=\"text-align: left;\">\n                            <strong>Nanny: </strong> tcp://127.0.0.1:34191\n                        </td>\n                        <td style=\"text-align: left;\"></td>\n                    </tr>\n                    <tr>\n                        <td colspan=\"2\" style=\"text-align: left;\">\n                            <strong>Local directory: </strong> /tmp/dask-scratch-space/worker-wo8fufhu\n                        </td>\n                    </tr>\n\n                    \n\n                    \n\n                </table>\n            </details>\n            </div>\n        </div>\n        \n\n    </details>\n</div>\n\n        </details>\n    </div>\n</div>\n            </details>\n        \n\n    </div>\n</div>","content_type":"text/html"}}},"key":"sLqtkNTR3F"}],"key":"wrZNpBbDh9"}],"key":"F74a41Nmvy"},{"type":"block","kind":"notebook-content","children":[{"type":"paragraph","position":{"start":{"line":1,"column":1},"end":{"line":1,"column":1}},"children":[{"type":"text","value":"☝️ Click the Dashboard link above.","position":{"start":{"line":1,"column":1},"end":{"line":1,"column":1}},"key":"rmNTTiNSDE"}],"key":"DQlJd0LUAH"},{"type":"paragraph","position":{"start":{"line":3,"column":1},"end":{"line":3,"column":1}},"children":[{"type":"text","value":"👈 Or click the “Search” 🔍 button in the dask-labextension dashboard.","position":{"start":{"line":3,"column":1},"end":{"line":3,"column":1}},"key":"WP1m8wSMUY"}],"key":"xkEVY18Rvz"}],"key":"VSU6mSpn9H"},{"type":"block","kind":"notebook-content","children":[{"type":"paragraph","position":{"start":{"line":1,"column":1},"end":{"line":1,"column":1}},"children":[{"type":"text","value":"If no arguments are specified in ","position":{"start":{"line":1,"column":1},"end":{"line":1,"column":1}},"key":"mRAzfHGqS0"},{"type":"inlineCode","value":"LocalCluster","position":{"start":{"line":1,"column":1},"end":{"line":1,"column":1}},"key":"JzhnKjwgWT"},{"type":"text","value":" it will automatically detect the number of CPU cores your system has and the amount of memory and create workers to appropriately fill that.","position":{"start":{"line":1,"column":1},"end":{"line":1,"column":1}},"key":"RRCp7EcXXc"}],"key":"amnSCwfNkV"},{"type":"paragraph","position":{"start":{"line":3,"column":1},"end":{"line":3,"column":1}},"children":[{"type":"text","value":"A ","position":{"start":{"line":3,"column":1},"end":{"line":3,"column":1}},"key":"RomejpUgyI"},{"type":"inlineCode","value":"LocalCluster","position":{"start":{"line":3,"column":1},"end":{"line":3,"column":1}},"key":"BiJNEF1Qp0"},{"type":"text","value":" will use the full resources of the current JupyterLab session.  For example, if you used BinderHub, it will use the number of CPUs selected.","position":{"start":{"line":3,"column":1},"end":{"line":3,"column":1}},"key":"dy2EDJkK93"}],"key":"YLznX2mlyO"},{"type":"paragraph","position":{"start":{"line":5,"column":1},"end":{"line":5,"column":1}},"children":[{"type":"text","value":"Note that ","position":{"start":{"line":5,"column":1},"end":{"line":5,"column":1}},"key":"DNg0X00ziQ"},{"type":"inlineCode","value":"LocalCluster()","position":{"start":{"line":5,"column":1},"end":{"line":5,"column":1}},"key":"YWzcG80zS7"},{"type":"text","value":" takes a lot of optional arguments, allowing you to configure the number of processes/threads, memory limits and other settings.","position":{"start":{"line":5,"column":1},"end":{"line":5,"column":1}},"key":"UXjOriv9Sr"}],"key":"p6LkqLBfC9"}],"key":"aPjy3YCT5r"},{"type":"block","kind":"notebook-content","children":[{"type":"paragraph","position":{"start":{"line":1,"column":1},"end":{"line":1,"column":1}},"children":[{"type":"text","value":"You can also find your cluster dashboard link using :","position":{"start":{"line":1,"column":1},"end":{"line":1,"column":1}},"key":"WcXCQImmxK"}],"key":"oUiZ5ylYzf"}],"key":"HUn3TWdCaB"},{"type":"block","kind":"notebook-code","children":[{"type":"code","lang":"python","executable":true,"value":"cluster.dashboard_link","key":"AWow0MAcS2"},{"type":"outputs","id":"iLtTcLq358-UNOFEGKZwx","children":[{"type":"output","children":[],"jupyter_data":{"output_type":"execute_result","execution_count":8,"metadata":{},"data":{"text/plain":{"content":"'http://127.0.0.1:33905/status'","content_type":"text/plain"}}},"key":"Agie4qZRSF"}],"key":"nFtts9311s"}],"key":"xKXFUoKw7E"},{"type":"block","kind":"notebook-code","children":[{"type":"code","lang":"python","executable":true,"value":"%%time\n# -- dask array using the default\nxd = da.random.normal(10, 0.1, size=(30_000, 30_000), chunks=(3000, 3000))\nyd = xd.mean(axis=0)\nyd.compute()","key":"RNhOiVOq18"},{"type":"outputs","id":"0egnhBDazEnhjmSBQMNOX","children":[{"type":"output","children":[],"jupyter_data":{"output_type":"stream","name":"stdout","text":"CPU times: user 1.1 s, sys: 173 ms, total: 1.27 s\nWall time: 23.7 s\n"},"key":"oFmkBijjaB"},{"type":"output","children":[],"jupyter_data":{"output_type":"execute_result","execution_count":9,"metadata":{},"data":{"text/plain":{"content":"array([10.00061805,  9.9997688 ,  9.99996876, ...,  9.99997053,\n       10.00014106,  9.99938061], shape=(30000,))","content_type":"text/plain"}}},"key":"KmRaiqlzqU"}],"key":"D1UaXKy6cQ"}],"key":"tuMjZGfGPI"},{"type":"block","kind":"notebook-content","children":[{"type":"paragraph","position":{"start":{"line":1,"column":1},"end":{"line":1,"column":1}},"children":[{"type":"text","value":"Always remember to close your local Dask cluster:","position":{"start":{"line":1,"column":1},"end":{"line":1,"column":1}},"key":"p9eRd7wNqL"}],"key":"qGYVMaxSxL"}],"key":"kcTLAvFvrS"},{"type":"block","kind":"notebook-code","children":[{"type":"code","lang":"python","executable":true,"value":"client.shutdown()","key":"a5TG1N2QII"},{"type":"outputs","id":"sM2QLnHDGhQIstMNupIbV","children":[],"key":"wOFZRYVjfh"}],"key":"gM5Vy8GBRA"},{"type":"block","kind":"notebook-content","children":[{"type":"heading","depth":3,"position":{"start":{"line":1,"column":1},"end":{"line":1,"column":1}},"children":[{"type":"text","value":"Dask Distributed (Cluster Managers)","position":{"start":{"line":1,"column":1},"end":{"line":1,"column":1}},"key":"vXYXck9dKl"}],"identifier":"dask-distributed-cluster-managers","label":"Dask Distributed (Cluster Managers)","html_id":"dask-distributed-cluster-managers","implicit":true,"key":"luF8ZdiuIf"},{"type":"paragraph","position":{"start":{"line":3,"column":1},"end":{"line":3,"column":1}},"children":[{"type":"text","value":"So far we have talked about running a job on a local machine.","position":{"start":{"line":3,"column":1},"end":{"line":3,"column":1}},"key":"XDgkkQa2Qz"}],"key":"erRMqB27aR"},{"type":"paragraph","position":{"start":{"line":5,"column":1},"end":{"line":5,"column":1}},"children":[{"type":"text","value":"Dask can be deployed on distributed infrastructure, such as a an HPC system or a cloud computing system.","position":{"start":{"line":5,"column":1},"end":{"line":5,"column":1}},"key":"eSkasdjYYX"}],"key":"ocGsHKFj1N"},{"type":"image","style":{"verticalAlign":"middle","margin":"30px 0px"},"url":"/dask-cookbook/_preview/30/build/5bb4678f8c7e666155eecf57b9320e34.svg","alt":"High level collections are used to generate task graphs which can be executed by schedulers on a single machine or a cluster.","width":"75%","key":"tYKeHA8oyb","urlSource":"https://docs.dask.org/en/stable/_images/dask-cluster-manager.svg"},{"type":"paragraph","position":{"start":{"line":9,"column":1},"end":{"line":9,"column":1}},"children":[{"type":"emphasis","position":{"start":{"line":9,"column":1},"end":{"line":9,"column":1}},"children":[{"type":"text","value":"Image credit: Dask Contributors","position":{"start":{"line":9,"column":1},"end":{"line":9,"column":1}},"key":"evUhUXb4xj"}],"key":"lV5Ut02Sb8"}],"key":"I2IAFIqyQ5"},{"type":"paragraph","position":{"start":{"line":11,"column":1},"end":{"line":11,"column":1}},"children":[{"type":"text","value":"Dask Cluster Managers have different names corresponding to different computing environments. Some examples are ","position":{"start":{"line":11,"column":1},"end":{"line":11,"column":1}},"key":"cYcSeZLyTl"},{"type":"inlineCode","value":"dask-jobqueue","position":{"start":{"line":11,"column":1},"end":{"line":11,"column":1}},"key":"yBSPfECwQ2"},{"type":"text","value":" for your HPC systems (including ","position":{"start":{"line":11,"column":1},"end":{"line":11,"column":1}},"key":"bLPMfUYBS7"},{"type":"inlineCode","value":"PBSCluster","position":{"start":{"line":11,"column":1},"end":{"line":11,"column":1}},"key":"D9JlMUUAjC"},{"type":"text","value":") or Kubernetes Cluster for machines on the Cloud.","position":{"start":{"line":11,"column":1},"end":{"line":11,"column":1}},"key":"CcuTUPhtWm"}],"key":"BkDw984QwO"},{"type":"paragraph","position":{"start":{"line":13,"column":1},"end":{"line":13,"column":1}},"children":[{"type":"text","value":"The NCAR tutorial series includes an in-depth exploration and practical use cases of Dask on HPC systems and best practices for Dask on HPC. For the complete set of NCAR tutorial materials, please refer to the main NCAR tutorial content available ","position":{"start":{"line":13,"column":1},"end":{"line":13,"column":1}},"key":"fFt0ySCMlp"},{"type":"link","url":"https://ncar.github.io/dask-tutorial/README.html","position":{"start":{"line":13,"column":1},"end":{"line":13,"column":1}},"children":[{"type":"text","value":"here","position":{"start":{"line":13,"column":1},"end":{"line":13,"column":1}},"key":"RiraIRuZug"}],"urlSource":"https://ncar.github.io/dask-tutorial/README.html","key":"o0JKRdJQ83"},{"type":"text","value":".","position":{"start":{"line":13,"column":1},"end":{"line":13,"column":1}},"key":"OC15ssHgXJ"}],"key":"eDC7nfU4ld"},{"type":"paragraph","position":{"start":{"line":15,"column":1},"end":{"line":15,"column":1}},"children":[{"type":"text","value":"For more information visit the ","position":{"start":{"line":15,"column":1},"end":{"line":15,"column":1}},"key":"phhvJ46gvQ"},{"type":"link","url":"https://docs.dask.org/en/stable/deploying.html","position":{"start":{"line":15,"column":1},"end":{"line":15,"column":1}},"children":[{"type":"text","value":"Dask Docs","position":{"start":{"line":15,"column":1},"end":{"line":15,"column":1}},"key":"b8Bs4ORN3V"}],"urlSource":"https://docs.dask.org/en/stable/deploying.html","key":"ZHlg0zz1gw"},{"type":"text","value":".","position":{"start":{"line":15,"column":1},"end":{"line":15,"column":1}},"key":"vm1F8rrjb9"}],"key":"rLBetsICYU"}],"key":"JzQY132aFG"}],"key":"K10UCu2ZMM"},"references":{"cite":{"order":[],"data":{}}},"footer":{"navigation":{"prev":{"title":"Dask DataFrame","url":"/notebooks/dask-dataframe","group":"Introductions to Dask"},"next":{"title":"Parallelizing Xarray with Dask","url":"/notebooks/dask-xarray","group":"Dask and Xarray"}}},"domain":"http://localhost:3000"}